climanu/__init__.py
climanu/climanu.py
climanu-0.0.1.dist-info/LICENSE
climanu-0.0.1.dist-info/METADATA
climanu-0.0.1.dist-info/WHEEL
climanu-0.0.1.dist-info/top_level.txt
climanu-0.0.1.dist-info/RECORD
