Metadata-Version: 2.1
Name: climanu
Version: 0.0.1
Summary: A cli project to make many type of chosser menu
Author: Hui Hola
Keywords: cli app,create you own simple manu,python3
Classifier: License :: OSI Approved :: MIT License
Classifier: Operating System :: OS Independent
Requires-Python: >=3.11.8
License-File: LICENSE
